MANIFEST.in
setup.py
kayako/README.txt
kayako/__init__.py
kayako/api.py
kayako/exception.py
kayako.egg-info/PKG-INFO
kayako.egg-info/SOURCES.txt
kayako.egg-info/dependency_links.txt
kayako.egg-info/entry_points.txt
kayako.egg-info/requires.txt
kayako.egg-info/top_level.txt
kayako.egg-info/zip-safe
kayako/core/__init__.py
kayako/core/lib.py
kayako/core/object.py
kayako/objects/__init__.py
kayako/objects/department.py
kayako/objects/staff.py
kayako/objects/user.py
kayako/objects/ticket/__init__.py
kayako/objects/ticket/ticket.py
kayako/objects/ticket/ticket_attachment.py
kayako/objects/ticket/ticket_count.py
kayako/objects/ticket/ticket_custom_field.py
kayako/objects/ticket/ticket_enums.py
kayako/objects/ticket/ticket_note.py
kayako/objects/ticket/ticket_post.py
kayako/objects/ticket/ticket_time_track.py
kayako/tests/__init__.py
kayako/tests/test_api.py
kayako/tests/test_exception.py
kayako/tests/core/__init__.py
kayako/tests/core/test_kayako_request_parser.py
kayako/tests/core/test_kayko_object.py
kayako/tests/core/test_node_parser.py
kayako/tests/core/test_parameter_object.py
kayako/tests/object/__init__.py
kayako/tests/object/test_department.py
kayako/tests/object/test_staff.py
kayako/tests/object/test_ticket.py
kayako/tests/object/test_ticket_attachment.py
kayako/tests/object/test_ticket_count.py
kayako/tests/object/test_ticket_custom_field.py
kayako/tests/object/test_ticket_enums.py
kayako/tests/object/test_ticket_note.py
kayako/tests/object/test_ticket_post.py
kayako/tests/object/test_ticket_search.py
kayako/tests/object/test_ticket_time_track.py
kayako/tests/object/test_user.py