Metadata-Version: 1.0
Name: kayako
Version: 1.1.5
Summary: Python API Wrapper for Kayako 4.01.240
Home-page: UNKNOWN
Author: Evan Leis
Author-email: engineergod@yahoo.com
License: Lesser GNU General Public License (LGPL)
Platform: UNKNOWN
Classifier: Programming Language :: Python
Classifier: Programming Language :: Python :: 2.6
Classifier: Development Status :: 4 - Beta
Classifier: Environment :: Other Environment
Classifier: Intended Audience :: Developers
Classifier: License :: OSI Approved :: GNU Library or Lesser General Public License (LGPL)
Classifier: Operating System :: OS Independent
Classifier: Topic :: Software Development :: Libraries :: Python Modules
